pymarketstore/__init__.py
pymarketstore/client.py
pymarketstore/jsonrpc.py
pymarketstore/results.py
pymarketstore/stream.py
pymarketstore2-0.17.dist-info/LICENSE
pymarketstore2-0.17.dist-info/METADATA
pymarketstore2-0.17.dist-info/WHEEL
pymarketstore2-0.17.dist-info/top_level.txt
pymarketstore2-0.17.dist-info/RECORD
