Metadata-Version: 2.1
Name: pymarketstore2
Version: 0.17
Summary: Marketstore python driver
Home-page: https://github.com/xmurobi/pymarketstore
Author: Alpaca
Author-email: oss@alpaca.markets
License: UNKNOWN
Keywords: database,pandas,financial,timeseries
Platform: UNKNOWN
Requires-Dist: msgpack-python
Requires-Dist: numpy
Requires-Dist: requests
Requires-Dist: pandas
Requires-Dist: six
Requires-Dist: urllib3
Requires-Dist: pytest
Requires-Dist: websocket-client
